Metadata-Version: 2.1
Name: qwdb.server
Version: 3.3.1
Summary: An improbable web debugger through WebSockets (server)
Home-page: http://github.com/Kozea/wdb
Author: Florian Mounier @ kozea
Author-email: florian.mounier@kozea.fr
License: GPLv3
Platform: Any
Classifier: Development Status :: 4 - Beta
Classifier: Intended Audience :: Developers
Classifier: License :: OSI Approved :: GNU General Public License v3 (GPLv3)
Classifier: Operating System :: OS Independent
Classifier: Programming Language :: Python :: 2
Classifier: Programming Language :: Python :: 3
Classifier: Programming Language :: Python :: Implementation :: CPython
Classifier: Programming Language :: Python :: Implementation :: PyPy
Classifier: Topic :: Software Development :: Debuggers
Requires-Dist: qwdb ==3.3.1
Requires-Dist: tornado >=5.0
Requires-Dist: psutil >=2.1
Requires-Dist: tornado-systemd
Requires-Dist: pyinotify
